teleapp_auth-1.0.1.dist-info/METADATA
teleapp_auth-1.0.1.dist-info/WHEEL
teleapp_auth/__init__.py
teleapp_auth/__init__.pyi
teleapp_auth/py.typed
teleapp_auth/teleapp_auth.cpython-311-darwin.so
teleapp_auth-1.0.1.dist-info/RECORD
