Metadata-Version: 2.3
Name: teleapp-auth
Version: 1.0.1
Classifier: Development Status :: 4 - Beta
Classifier: Intended Audience :: Developers
Classifier: License :: OSI Approved :: MIT License
Classifier: Programming Language :: Python
Classifier: Programming Language :: Python :: 3
Classifier: Programming Language :: Python :: 3.9
Classifier: Programming Language :: Python :: 3.10
Classifier: Programming Language :: Python :: 3.11
Classifier: Programming Language :: Python :: 3.12
Classifier: Operating System :: OS Independent
Classifier: Topic :: Software Development :: Libraries
Classifier: Topic :: Internet :: WWW/HTTP
Summary: 🚀 A Rust-based Python package for validating Telegram WebApp authorization.
Keywords: telegram,webapp,authentication,auth,web,python,api,bot,security,miniapp,teleapp,teleapp-auth
Author-email: vffuunnyy <vffuunnyy@gmail.com>
License: MIT
Requires-Python: >=3.9.0
Project-URL: Homepage, https://github.com/vffuunnyy/teleapp_auth/
Project-URL: Documentation, https://github.com/vffuunnyy/teleapp_auth/
Project-URL: Repository, https://github.com/vffuunnyy/teleapp_auth.git
Project-URL: Issues, https://github.com/vffuunnyy/teleapp_auth/issues
